jumper/__init__.py
jumper/__main__.py
jumper/__version__.py
jumper/common.py
jumper/default_bsp.json
jumper/examples_hash_list.json
jumper/jemu_bma280.py
jumper/jemu_bme280.py
jumper/jemu_bq24160.py
jumper/jemu_bq27421.py
jumper/jemu_bsp_parser.py
jumper/jemu_button.py
jumper/jemu_connection.py
jumper/jemu_gpio.py
jumper/jemu_interrupts.py
jumper/jemu_mem_peripheral.py
jumper/jemu_peripheral.py
jumper/jemu_peripherals_parser.py
jumper/jemu_sudo.py
jumper/jemu_uart.py
jumper/jemu_uart_tcp.py
jumper/jemu_web_api.py
jumper/vlab.py
jumper/vlab_hci_device.py
jumper/hci/hci
jumper/hci/instructions.so
jumper/hci/peripherals.json
jumper/hci/program.bin
jumper-0.1.27.dist-info/DESCRIPTION.rst
jumper-0.1.27.dist-info/METADATA
jumper-0.1.27.dist-info/RECORD
jumper-0.1.27.dist-info/WHEEL
jumper-0.1.27.dist-info/entry_points.txt
jumper-0.1.27.dist-info/metadata.json
jumper-0.1.27.dist-info/top_level.txt
