Metadata-Version: 2.0
Name: jumper
Version: 0.1.27
Summary: SDK for using Jumper's emulator
Home-page: https://vlab.jumper.io
Author: Jumper Labs Ltd.
Author-email: info@jumper.io
License: Apache 2.0
Platform: UNKNOWN
Classifier: Development Status :: 3 - Alpha
Classifier: Programming Language :: Python :: 2.7
Requires-Python: ==2.7.*
Provides-Extra: dev
Requires-Dist: future
Requires-Dist: timeout-decorator
Requires-Dist: requests
Requires-Dist: termcolor
Requires-Dist: terminaltables
Provides-Extra: dev
Requires-Dist: sphinx; extra == 'dev'
Requires-Dist: nose; extra == 'dev'
Requires-Dist: sphinx-bootstrap-theme; extra == 'dev'
Requires-Dist: sphinx-rtd-theme; extra == 'dev'
Requires-Dist: twine; extra == 'dev'
Requires-Dist: wheel; extra == 'dev'
